goliath_client/__init__.py
goliath_client/client.py
goliath_client/list_models.yaml
goliath_client/models.py
goliath_llm_client-0.1.1.dist-info/LICENSE
goliath_llm_client-0.1.1.dist-info/METADATA
goliath_llm_client-0.1.1.dist-info/WHEEL
goliath_llm_client-0.1.1.dist-info/top_level.txt
goliath_llm_client-0.1.1.dist-info/RECORD
